cloudnetdraw/__init__.py
cloudnetdraw/__main__.py
cloudnetdraw/azure_client.py
cloudnetdraw/cli.py
cloudnetdraw/config.py
cloudnetdraw/diagram_generator.py
cloudnetdraw/edge_system.py
cloudnetdraw/layout.py
cloudnetdraw/topology.py
cloudnetdraw/utils.py
cloudnetdraw/data/config.yaml
cloudnetdraw-0.1.7.dist-info/METADATA
cloudnetdraw-0.1.7.dist-info/WHEEL
cloudnetdraw-0.1.7.dist-info/entry_points.txt
cloudnetdraw-0.1.7.dist-info/licenses/LICENSE
cloudnetdraw-0.1.7.dist-info/RECORD
