Metadata-Version: 2.4
Name: cloudnetdraw
Version: 0.1.7
Summary: Azure VNet topology discovery and visualization tool that generates Draw.io diagrams
Project-URL: Homepage, https://www.cloudnetdraw.com/
Project-URL: Repository, https://github.com/krhatland/cloudnet-draw.git
Project-URL: Issues, https://github.com/krhatland/cloudnet-draw/issues
Project-URL: Documentation, https://github.com/krhatland/cloudnet-draw#readme
Project-URL: Changelog, https://github.com/krhatland/cloudnet-draw/releases
Project-URL: Blog, https://hatnes.no/posts/cloudnet-draw/
Author: CloudNet Draw Contributors
License: MIT License
License-File: LICENSE
Keywords: azure,drawio,network,topology,visualization,vnet
Classifier: Development Status :: 4 - Beta
Classifier: Intended Audience :: Developers
Classifier: Intended Audience :: System Administrators
Classifier: License :: OSI Approved :: MIT License
Classifier: Operating System :: OS Independent
Classifier: Programming Language :: Python :: 3
Classifier: Topic :: System :: Networking
Classifier: Topic :: System :: Systems Administration
Classifier: Topic :: Utilities
Requires-Python: >=3.8
Requires-Dist: azure-identity>=1.15.0
Requires-Dist: azure-mgmt-network>=25.0.0
Requires-Dist: azure-mgmt-resource>=23.0.0
Requires-Dist: azure-mgmt-resourcegraph>=8.0.0
Requires-Dist: importlib-resources>=1.3.0; python_version < '3.9'
Requires-Dist: lxml>=4.9.0
Requires-Dist: pyyaml>=6.0
Requires-Dist: six>=1.16.0
Provides-Extra: dev
Requires-Dist: pytest-cov>=4.0.0; extra == 'dev'
Requires-Dist: pytest-mock>=3.10.0; extra == 'dev'
Requires-Dist: pytest>=7.0.0; extra == 'dev'
